{
    "mobileBottomRow": 126,
    "widgetName": "SwitchGroup1",
    "isCanvas": false,
    "displayName": "Switch Group",
    "iconSVG": "/static/media/icon.6a5a5f62190c8b357935095e946a663c.svg",
    "labelText": "Label",
    "topRow": 120,
    "bottomRow": 126,
    "parentRowSpace": 10,
    "labelWidth": 5,
    "type": "SWITCH_GROUP_WIDGET",
    "hideCard": false,
    "mobileRightColumn": 26,
    "animateLoading": true,
    "parentColumnSpace": 12.578125,
    "dynamicTriggerPathList": [],
    "leftColumn": 10,
    "dynamicBindingPathList": [{"key": "accentColor"}],
    "labelPosition": "Top",
    "options": "[\n  {\n    \"label\": \"Blue\",\n    \"value\": \"BLUE\"\n  },\n  {\n    \"label\": \"Green\",\n    \"value\": \"GREEN\"\n  },\n  {\n    \"label\": \"Red\",\n    \"value\": \"RED\"\n  }\n]",
    "isDisabled": false,
    "key": "hyz4v9anw0",
    "labelTextSize": "0.875rem",
    "isRequired": false,
    "isDeprecated": false,
    "rightColumn": 48,
    "defaultSelectedValues": ["BLUE"],
    "dynamicHeight": "AUTO_HEIGHT",
    "widgetId": "6redqjsclr",
    "accentColor": "{{appsmith.theme.colors.primaryColor}}",
    "isVisible": true,
    "version": 1,
    "parentId": "0",
    "tags": ["Toggles"],
    "labelAlignment": "left",
    "renderMode": "CANVAS",
    "isLoading": false,
    "mobileTopRow": 120,
    "originalTopRow": 120,
    "mobileLeftColumn": 0,
    "maxDynamicHeight": 9000,
    "originalBottomRow": 126,
    "isInline": true,
    "alignment": "left",
    "minDynamicHeight": 4
}