{
    "isRequired": false,
    "widgetName": "status_dropdown",
    "rightColumn": 61,
    "isFilterable": true,
    "widgetId": "pnny8dt51a",
    "topRow": 2,
    "bottomRow": 6,
    "parentRowSpace": 40,
    "isVisible": true,
    "label": "",
    "type": "DROP_DOWN_WIDGET",
    "version": 1,
    "parentId": "fi1mfel9i0",
    "isLoading": false,
    "defaultOptionValue": "All",
    "parentColumnSpace": 74,
    "dynamicTriggerPathList": [{"key": "onOptionChange"}],
    "leftColumn": 50,
    "dynamicBindingPathList": [],
    "options": "[\n{\n    \"label\": \"All\",\n    \"value\": \"All\"\n  },\n  {\n    \"label\": \"Applied\",\n    \"value\": \"Applied\"\n  },\n  {\n    \"label\": \"Contacted\",\n    \"value\": \"Contacted\"\n  },\n  {\n    \"label\": \"Interview Scheduled\",\n    \"value\": \"Interview Scheduled\"\n  },\n\t{\n    \"label\": \"Feedback Received\",\n    \"value\": \"Feedback Received\"\n  },\n\t{\n    \"label\": \"Candidate Rejected\",\n    \"value\": \"Candidate Rejected\"\n  },\n\t{\n    \"label\": \"Offer Made\",\n    \"value\": \"Offer Made\"\n  },\n\t{\n    \"label\": \"Offer Accepted\",\n    \"value\": \"Offer Accepted\"\n  },\n\t{\n    \"label\": \"Offer Rejected\",\n    \"value\": \"Offer Rejected\"\n  }\n]",
    "onOptionChange": "{{getApplications.run()}}",
    "isDisabled": false
}